<?xml version="1.0" encoding="UTF-8"?><activity class="mm_unit4 mm_activity11" id="348661f45fb748da82d3ffba4f24776a" pseudoID="BT_L1_U4_GAME_11">
    <metadata>
        <title>Lesson 5 – activity 1</title>
        <category>Games</category>
    </metadata>
    <rubric>
        <audio size="large" srt="y">
            <track src="BT1_CD2.30.mp3"/>
        </audio>
        <p>Listen to the chant and choose the correct pictures.</p>
    </rubric>
    <main>
        <block>
            <list display="v" type="numbered">
                <li>
                    <radio id="radio_1" display="h" displayType="itemSelect" name="" type="plain">
                        <item id="item_1" correct="y">
                            <image src="monkey1a.psd" title=""/>
                        </item>
                        <item id="item_2">
                            <image src="monkey1b.psd" title=""/>
                        </item>
                    </radio>
                </li>
                <li>
                    <radio id="radio_2" display="h" displayType="itemSelect" name="" type="plain">
                        <item id="item_1">
                            <image src="parrot2a.psd" title=""/>
                        </item>
                        <item id="item_2" correct="y">
                            <image src="parrot2b.psd" title=""/>
                        </item>
                    </radio>
                </li>
                <li>
                    <radio id="radio_3" display="h" displayType="itemSelect" name="" type="plain">
                        <item id="item_1" correct="y">
                            <image src="giraffe3a.psd" title=""/>
                        </item>
                        <item id="item_2">
                            <image src="giraffe3b.psd" title=""/>
                        </item>
                    </radio>
                </li>
                <li>
                    <radio id="radio_4" display="h" displayType="itemSelect" name="" type="plain">
                        <item id="item_1">
                            <image src="zebra4a.psd" title=""/>
                        </item>
                        <item id="item_2" correct="y">
                            <image src="zebra4b.psd" title=""/>
                        </item>
                    </radio>
                </li>
                <li>
                    <radio id="radio_5" display="h" displayType="itemSelect" name="" type="plain">
                        <item id="item_1" correct="y">
                            <image src="hippo5a.psd" title=""/>
                        </item>
                        <item id="item_2">
                            <image src="hippo5b.psd" title=""/>
                        </item>
                    </radio>
                </li>
                <li>
                    <radio id="radio_6" display="h" displayType="itemSelect" name="" type="plain">
                        <item id="item_1">
                            <image src="elephant6a.psd" title=""/>
                        </item>
                        <item id="item_2" correct="y">
                            <image src="elephant6b.psd" title=""/>
                        </item>
                    </radio>
                </li>
            </list>
        </block>
    </main>
</activity>
